SRT_H/SRT_H.py
SRT_H/__init__.py
srt_h-0.0.16.dist-info/METADATA
srt_h-0.0.16.dist-info/WHEEL
srt_h-0.0.16.dist-info/licenses/LICENSE
srt_h-0.0.16.dist-info/RECORD
