Metadata-Version: 2.4
Name: SRT-H
Version: 0.0.16
Summary: SRT-H
Project-URL: Homepage, https://pypi.org/project/SRT-H/
Project-URL: Repository, https://github.com/lucidrains/SRT-H
Author-email: Phil Wang <lucidrains@gmail.com>
License: MIT License
License-File: LICENSE
Keywords: artificial intelligence,attention mechanism,deep learning,surgical-robotics,transformers
Classifier: Development Status :: 4 - Beta
Classifier: Intended Audience :: Developers
Classifier: License :: OSI Approved :: MIT License
Classifier: Programming Language :: Python :: 3.9
Classifier: Topic :: Scientific/Engineering :: Artificial Intelligence
Requires-Python: >=3.9
Requires-Dist: autofaiss
Requires-Dist: bidirectional-cross-attention>=0.1.0
Requires-Dist: einops>=0.8.0
Requires-Dist: einx>=0.3.0
Requires-Dist: rectified-flow-pytorch
Requires-Dist: requests
Requires-Dist: timm
Requires-Dist: torch>=2.0
Requires-Dist: transformers>=4.54.1
Requires-Dist: validators
Requires-Dist: vit-pytorch>=1.11.4
Requires-Dist: x-transformers>=2.5.6
Provides-Extra: examples
Provides-Extra: test
Requires-Dist: pytest; extra == 'test'
